tobool/__init__.py
tobool/__version__.py
tobool/py.typed
tobool/tobool.py
tobool-0.4.0.dist-info/LICENSE
tobool-0.4.0.dist-info/METADATA
tobool-0.4.0.dist-info/WHEEL
tobool-0.4.0.dist-info/top_level.txt
tobool-0.4.0.dist-info/RECORD
