Metadata-Version: 2.1
Name: tobool
Version: 0.4.0
Summary: convert any boolean-like value such as string, int, etc. to an actual bool
Home-page: https://github.com/jamesabel/tobool
Download-URL: https://github.com/jamesabel/tobool
Author: abel
Author-email: j@abel.co
License: MIT License
Keywords: boolean
License-File: LICENSE
